rslurm/__init__.py
rslurm/__main__.py
rslurm/config.py
rslurm/rslurm.py
rslurm-0.0.1.dist-info/METADATA
rslurm-0.0.1.dist-info/WHEEL
rslurm-0.0.1.dist-info/top_level.txt
rslurm-0.0.1.dist-info/RECORD
