Metadata-Version: 2.1
Name: rslurm
Version: 0.0.1
Summary: Helps to run remote jobs easily.
Home-page: https://github.com/ysenarath/rslurm
Author: Yasas Senarath
License: UNKNOWN
Platform: UNKNOWN
Classifier: Programming Language :: Python :: 3
Classifier: License :: OSI Approved :: MIT License
Classifier: Operating System :: OS Independent
Requires-Python: >=3.6
Requires-Dist: click (>=8.0.4)
Requires-Dist: PyYAML (>=6.0)
Requires-Dist: fabric (>=2.6.0)
Requires-Dist: pip (>=21.1.2)
Requires-Dist: wheel (>=0.36.2)
Requires-Dist: cryptography (>=36.0.1)
Requires-Dist: setuptools (>=57.0.0)
